basestation_ctrl/__init__.py
basestation_ctrl/__main__.py
basestation_ctrl/basestation.py
basestation_ctrl/basestation_ctrl.py
basestation_ctrl/cli.py
basestation_ctrl-0.3.2.dist-info/LICENSE.txt
basestation_ctrl-0.3.2.dist-info/METADATA
basestation_ctrl-0.3.2.dist-info/WHEEL
basestation_ctrl-0.3.2.dist-info/entry_points.txt
basestation_ctrl-0.3.2.dist-info/top_level.txt
basestation_ctrl-0.3.2.dist-info/RECORD
