Metadata-Version: 2.1
Name: basestation-ctrl
Version: 0.3.2
Summary: Library and CLI to wake up / power down SteamVR (Lighthouse) Base Stations
Home-page: https://github.com/schlagenhauf/basestation-ctrl.git
Author: Jonas Schlagenhauf
Author-email: schlagenhauf_github@mailbox.org
License: MIT
Platform: any
Classifier: Development Status :: 4 - Beta
Classifier: Programming Language :: Python
Requires-Python: >=3.8
License-File: LICENSE.txt
Requires-Dist: click
Requires-Dist: bluepy
Requires-Dist: importlib-metadata ; python_version < "3.8"
Provides-Extra: testing
Requires-Dist: setuptools ; extra == 'testing'
Requires-Dist: pytest ; extra == 'testing'
Requires-Dist: pytest-cov ; extra == 'testing'
